terka/__init__.py
terka/bootstrap.py
terka/exceptions.py
terka/utils.py
terka/views.py
terka/adapters/__init__.py
terka/adapters/orm.py
terka/adapters/publisher.py
terka/adapters/repository.py
terka/domain/__init__.py
terka/domain/commands.py
terka/domain/events.py
terka/domain/entities/__init__.py
terka/domain/entities/collaborator.py
terka/domain/entities/commentary.py
terka/domain/entities/composite.py
terka/domain/entities/entity.py
terka/domain/entities/epic.py
terka/domain/entities/event_history.py
terka/domain/entities/note.py
terka/domain/entities/project.py
terka/domain/entities/sprint.py
terka/domain/entities/story.py
terka/domain/entities/tag.py
terka/domain/entities/task.py
terka/domain/entities/time_tracker.py
terka/domain/entities/user.py
terka/domain/entities/workspace.py
terka/domain/external_connectors/__init__.py
terka/domain/external_connectors/asana.py
terka/entrypoints/__init__.py
terka/entrypoints/server.py
terka/entrypoints/cli/__init__.py
terka/entrypoints/cli/epics.py
terka/entrypoints/cli/main.py
terka/entrypoints/cli/projects.py
terka/entrypoints/cli/sprints.py
terka/entrypoints/cli/stories.py
terka/entrypoints/cli/tags.py
terka/entrypoints/cli/tasks.py
terka/entrypoints/cli/users.py
terka/entrypoints/cli/workspaces.py
terka/presentations/__init__.py
terka/presentations/formatter.py
terka/presentations/console/__init__.py
terka/presentations/console/printer.py
terka/presentations/text_ui/__init__.py
terka/presentations/text_ui/components.py
terka/presentations/text_ui/ui.py
terka/presentations/text_ui/css/__init__.py
terka/presentations/text_ui/css/entities.css
terka/presentations/text_ui/css/vertical_layout.css
terka/presentations/vim/__init__.py
terka/presentations/vim/templates.py
terka/service_layer/__init__.py
terka/service_layer/handlers.py
terka/service_layer/messagebus.py
terka/service_layer/services.py
terka/service_layer/unit_of_work.py
terka-3.0.0.dist-info/licenses/LICENSE
terka-3.0.0.dist-info/METADATA
terka-3.0.0.dist-info/WHEEL
terka-3.0.0.dist-info/entry_points.txt
terka-3.0.0.dist-info/top_level.txt
terka-3.0.0.dist-info/RECORD
