Metadata-Version: 2.4
Name: terka
Version: 3.0.0
Summary: CLI utility for creating and managing tasks in a terminal
Author-email: Andrei Markin <andrey.markin.ppc@gmail.com>
Classifier: Development Status :: 4 - Beta
Classifier: Programming Language :: Python
Requires-Python: >=3.10
License-File: LICENSE
Requires-Dist: sqlalchemy==1.4.0
Requires-Dist: pyaml
Requires-Dist: rich
Requires-Dist: textual==0.41.0
Requires-Dist: plotext==5.2.8
Requires-Dist: textual-plotext==0.2.1
Requires-Dist: pandas
Requires-Dist: matplotlib
Requires-Dist: typer
Provides-Extra: asana
Requires-Dist: asana; extra == "asana"
Provides-Extra: all
Requires-Dist: terka[asana]; extra == "all"
Dynamic: license-file
